README.md
setup.cfg
setup.py
redisconnection.egg-info/PKG-INFO
redisconnection.egg-info/SOURCES.txt
redisconnection.egg-info/dependency_links.txt
redisconnection.egg-info/requires.txt
redisconnection.egg-info/top_level.txt
src/redisconnection/__init__.py
src/redisconnection/redis_connection.py
test/test.py