Metadata-Version: 1.1
Name: redisconnection
Version: 0.0.4
Summary: Redis Connections and Queries Handler
Home-page: https://github.com/ByPrice/redisconnection
Author: Yogesh Yadav
Author-email: yogeshdtu@gmail.com
License: MIT
Download-URL: https://github.com/ByPrice/redisconnection
Keywords: redis,redis-queries,redis-connection-wrapper
Platform: cross-platfom
Platform: platform-independent
Classifier: Development Status :: 3 - Alpha
Classifier: Intended Audience :: Developers
Classifier: Topic :: Software Development :: Build Tools
Classifier: Programming Language :: Python :: 3.6
